<nem>
    <nem0>
        <mass>10.300000</mass>
        <velocity>
            <x>1.000000</x>
            <y>14.670000</y>
        </velocity>
        <forces>
            <x>10.600000</x>
            <y>1.560000</y>
        </forces>
        <position>
            <x>0.000000</x>
            <y>0.000000</y>
        </position>
    </nem0>
    <nem1>
        <mass>10.300000</mass>
        <velocity>
            <x>1.000000</x>
            <y>14.670000</y>
        </velocity>
        <forces>
            <x>10.600000</x>
            <y>1.560000</y>
        </forces>
        <position>
            <x>0.000000</x>
            <y>0.000000</y>
        </position>
    </nem1>
    <nem2>
        <mass>10.300000</mass>
        <velocity>
            <x>1.000000</x>
            <y>14.670000</y>
        </velocity>
        <forces>
            <x>10.600000</x>
            <y>1.560000</y>
        </forces>
        <position>
            <x>0.000000</x>
            <y>0.000000</y>
        </position>
    </nem2>
    <nem3>
        <mass>10.300000</mass>
        <velocity>
            <x>1.000000</x>
            <y>14.670000</y>
        </velocity>
        <forces>
            <x>10.600000</x>
            <y>1.560000</y>
        </forces>
        <position>
            <x>0.000000</x>
            <y>0.000000</y>
        </position>
    </nem3>
    <nem4>
        <mass>10.300000</mass>
        <velocity>
            <x>1.000000</x>
            <y>14.670000</y>
        </velocity>
        <forces>
            <x>10.600000</x>
            <y>1.560000</y>
        </forces>
        <position>
            <x>0.000000</x>
            <y>0.000000</y>
        </position>
    </nem4>
    <nem5>
        <mass>10.300000</mass>
        <velocity>
            <x>1.000000</x>
            <y>14.670000</y>
        </velocity>
        <forces>
            <x>10.600000</x>
            <y>1.560000</y>
        </forces>
        <position>
            <x>0.000000</x>
            <y>0.000000</y>
        </position>
    </nem5>
    <nem6>
        <mass>10.300000</mass>
        <velocity>
            <x>1.000000</x>
            <y>14.670000</y>
        </velocity>
        <forces>
            <x>10.600000</x>
            <y>1.560000</y>
        </forces>
        <position>
            <x>0.000000</x>
            <y>0.000000</y>
        </position>
    </nem6>
    <nem7>
        <mass>10.300000</mass>
        <velocity>
            <x>1.000000</x>
            <y>14.670000</y>
        </velocity>
        <forces>
            <x>10.600000</x>
            <y>1.560000</y>
        </forces>
        <position>
            <x>0.000000</x>
            <y>0.000000</y>
        </position>
    </nem7>
</nem>
<player>
    <player0>
        <mass>2.700000</mass>
        <velocity>
            <x>0.000000</x>
            <y>0.000000</y>
        </velocity>
        <forces>
            <x>0.000000</x>
            <y>0.000000</y>
        </forces>
        <position>
            <x>0.000000</x>
            <y>0.000000</y>
        </position>
    </player0>
</player>
<rock>
    <rock0>
        <mass>1.000000</mass>
        <velocity>
            <x>0.000000</x>
            <y>0.000000</y>
        </velocity>
        <forces>
            <x>0.000000</x>
            <y>0.000000</y>
        </forces>
        <position>
            <x>0.000000</x>
            <y>10.000000</y>
        </position>
    </rock0>
</rock>
